interprog/__init__.py
interprog/py.typed
interprog-0.2.0.dist-info/WHEEL
interprog-0.2.0.dist-info/LICENSE.txt
interprog-0.2.0.dist-info/METADATA
interprog-0.2.0.dist-info/RECORD
