Metadata-Version: 2.1
Name: interprog
Version: 0.2.0
Summary: Inter-process progress reports made easy
Home-page: https://github.com/ThatXliner/interprog
License: MIT
Author: Bryan Hu
Author-email: bryan.hu.2020@gmail.com
Requires-Python: >=3.8,<4.0
Classifier: Development Status :: 4 - Beta
Classifier: License :: OSI Approved :: MIT License
Classifier: Natural Language :: English
Classifier: Operating System :: OS Independent
Classifier: Programming Language :: Python :: 3
Classifier: Programming Language :: Python :: 3.8
Classifier: Programming Language :: Python :: 3.9
Classifier: Programming Language :: Python :: 3.10
Classifier: Programming Language :: Python :: 3.11
Classifier: Programming Language :: Python :: Implementation :: CPython
Project-URL: Documentation, https://interprog.readthedocs.io/en/latest/index.html
